[
  {
    "id": 1,
    "image": "https://raw.githubusercontent.com/rean-site/api-edu-congress-2025/main/1.png",
    "title": "អនុសាសន៍របស់សម្តេចប្រធានក្រុមដឹកនាំ បក្ស ម៉ានីកា ធាយឡាន ក្នុងព្រះរាជពិធីប្រកាសបើក",
    "date": "2025-02-27 16:56:00",
    "description": "អនុសាសន៍របស់សម្តេចប្រធានក្រុមដឹកនាំ បក្ស ម៉ានីកា ធាយឡាន ថា សិស្សនិស្សិតគ្រប់រូប គួរតែបំពេញការសិក្សាឲ្យបានល្អ និងរួមចំណែកសំរាប់ការអភិវឌ្ឍសង្គមប្រទេសជាតិ។"
  },
  {
    "id": 2,
    "image": "https://raw.githubusercontent.com/rean-site/api-edu-congress-2025/main/2.png",
    "title": "ពិធីប្រគល់និទានបុណ្យសញ្ញាប័ត្រជូន យុវជន និងគ្រូបង្រៀន ឆ្នំាសិក្សា ២០២៣-២០២៤ និងនិទានឆ្នំាសិក្សា ២០២៤-២០២៥ ប្រកាសប្រសិទ្ធភាព",
    "date": "2025-02-26 22:10:00",
    "description": "ក្នុងសិទ្ធិសញ្ញាប័ត្រនេះ សម្តេចប្រធានក្រុមដឹកនាំ បក្ស ម៉ានីកា ធាយឡាន បានអបអរសាទរដល់សិស្ស និងគ្រូបង្រៀនទាំងអស់សម្រាប់ការខិតខំប្រឹងប្រែង និងការរួមចំណែកដល់ការអភិវឌ្ឍវិជ្ជាជីវៈ។"
  }
]
